gfapi-1.2.dist-info/METADATA
gfapi-1.2.dist-info/RECORD
gfapi-1.2.dist-info/WHEEL
gfapi-1.2.dist-info/top_level.txt
gluster/__init__.py
gluster/gfapi/__init__.py
gluster/gfapi/api.py
gluster/gfapi/exceptions.py
gluster/gfapi/gfapi.py
gluster/gfapi/utils.py
